{"name":"Complete a purchase with one product in cart","id":"saucedemo-purchase;complete-a-purchase-with-one-product-in-cart","scenarioId":"classpath:features/saucedemo:Complete a purchase with one product in cart","methodName":"Complete a purchase with one product in cart","testSteps":[{"number":1,"description":"Given the actor is on the login page","duration":6125,"startTime":"2026-03-12T13:55:42.639740600-05:00[America/Bogota]","screenshots":[{"screenshot":"6f313d1959d2fd7de3dabe61ef0d97acd789932ad03c97d58f7fe3fd73e40c57.png","timeStamp":1773341748777,"screenshotName":"6f313d1959d2fd7de3dabe61ef0d97acd789932ad03c97d58f7fe3fd73e40c57.png"}],"result":"SUCCESS","precondition":false,"level":0,"children":[{"number":2,"description":"Usuario opens the browser at https://www.saucedemo.com","duration":6108,"startTime":"2026-03-12T13:55:42.651773100-05:00[America/Bogota]","screenshots":[{"screenshot":"6f313d1959d2fd7de3dabe61ef0d97acd789932ad03c97d58f7fe3fd73e40c57.png","timeStamp":1773341748760,"screenshotName":"6f313d1959d2fd7de3dabe61ef0d97acd789932ad03c97d58f7fe3fd73e40c57.png"}],"result":"SUCCESS","precondition":false,"level":1}]},{"number":3,"description":"And the actor closes any browser notification","duration":5,"startTime":"2026-03-12T13:55:48.779916-05:00[America/Bogota]","screenshots":[{"screenshot":"6f313d1959d2fd7de3dabe61ef0d97acd789932ad03c97d58f7fe3fd73e40c57.png","timeStamp":1773341748803,"screenshotName":"6f313d1959d2fd7de3dabe61ef0d97acd789932ad03c97d58f7fe3fd73e40c57.png"}],"result":"SUCCESS","precondition":false,"level":0},{"number":4,"description":"Given the actor has logged in as standard user","duration":2914,"startTime":"2026-03-12T13:55:48.804931900-05:00[America/Bogota]","screenshots":[{"screenshot":"c930e0e29beb81d58e026ab60b4441345ab1fc23381426f0fad05f54f0716da0.png","timeStamp":1773341751735,"screenshotName":"c930e0e29beb81d58e026ab60b4441345ab1fc23381426f0fad05f54f0716da0.png"}],"result":"SUCCESS","precondition":false,"level":0,"children":[{"number":5,"description":"Usuario inicia sesión con usuario: standard_user","duration":2848,"startTime":"2026-03-12T13:55:48.860987700-05:00[America/Bogota]","screenshots":[{"screenshot":"c930e0e29beb81d58e026ab60b4441345ab1fc23381426f0fad05f54f0716da0.png","timeStamp":1773341751709,"screenshotName":"c930e0e29beb81d58e026ab60b4441345ab1fc23381426f0fad05f54f0716da0.png"}],"result":"SUCCESS","precondition":false,"level":1,"children":[{"number":6,"description":"Usuario enters \u0027standard_user\u0027 into campo de usuario","duration":851,"startTime":"2026-03-12T13:55:48.865041300-05:00[America/Bogota]","screenshots":[{"screenshot":"330cbe1d6fef0e970b24725c5b20e167e9612fca783ae6eacd0ce6874ca6a616.png","timeStamp":1773341749716,"screenshotName":"330cbe1d6fef0e970b24725c5b20e167e9612fca783ae6eacd0ce6874ca6a616.png"}],"result":"SUCCESS","precondition":false,"level":2},{"number":7,"description":"Usuario enters \u0027secret_sauce\u0027 into campo de contraseña","duration":724,"startTime":"2026-03-12T13:55:49.722533-05:00[America/Bogota]","screenshots":[{"screenshot":"d0b257546bea6224255713536800bca5995cab8d5ce85d45fe50cdf126a3450b.png","timeStamp":1773341750447,"screenshotName":"d0b257546bea6224255713536800bca5995cab8d5ce85d45fe50cdf126a3450b.png"}],"result":"SUCCESS","precondition":false,"level":2},{"number":8,"description":"Usuario clicks on botón de login","duration":1223,"startTime":"2026-03-12T13:55:50.463267600-05:00[America/Bogota]","screenshots":[{"screenshot":"c930e0e29beb81d58e026ab60b4441345ab1fc23381426f0fad05f54f0716da0.png","timeStamp":1773341751687,"screenshotName":"c930e0e29beb81d58e026ab60b4441345ab1fc23381426f0fad05f54f0716da0.png"}],"result":"SUCCESS","precondition":false,"level":2}]}]},{"number":9,"description":"And has the product \"Sauce Labs Backpack\" in the cart","duration":1420,"startTime":"2026-03-12T13:55:51.735217900-05:00[America/Bogota]","screenshots":[{"screenshot":"478dfd1128ea036b37dfe7df8ae80671069f3b29bc4114aeae6730502621a08f.png","timeStamp":1773341753167,"screenshotName":"478dfd1128ea036b37dfe7df8ae80671069f3b29bc4114aeae6730502621a08f.png"}],"result":"SUCCESS","precondition":false,"level":0,"children":[{"number":10,"description":"Usuario añade el producto Sauce Labs Backpack al carrito","duration":746,"startTime":"2026-03-12T13:55:51.758986500-05:00[America/Bogota]","screenshots":[{"screenshot":"2bc5e702aaaca8673f0c3fd9747b41613e10b7ba75cc9f45c76dc76f6c900dec.png","timeStamp":1773341752505,"screenshotName":"2bc5e702aaaca8673f0c3fd9747b41613e10b7ba75cc9f45c76dc76f6c900dec.png"}],"result":"SUCCESS","precondition":false,"level":1,"children":[{"number":11,"description":"Usuario clicks on botón añadir al carrito","duration":722,"startTime":"2026-03-12T13:55:51.765060400-05:00[America/Bogota]","screenshots":[{"screenshot":"2bc5e702aaaca8673f0c3fd9747b41613e10b7ba75cc9f45c76dc76f6c900dec.png","timeStamp":1773341752487,"screenshotName":"2bc5e702aaaca8673f0c3fd9747b41613e10b7ba75cc9f45c76dc76f6c900dec.png"}],"result":"SUCCESS","precondition":false,"level":2}]},{"number":12,"description":"Usuario clicks on enlace al carrito","duration":642,"startTime":"2026-03-12T13:55:52.509222700-05:00[America/Bogota]","screenshots":[{"screenshot":"478dfd1128ea036b37dfe7df8ae80671069f3b29bc4114aeae6730502621a08f.png","timeStamp":1773341753151,"screenshotName":"478dfd1128ea036b37dfe7df8ae80671069f3b29bc4114aeae6730502621a08f.png"}],"result":"SUCCESS","precondition":false,"level":1}]},{"number":13,"description":"When proceeds to checkout and completes shipping information","duration":4953,"startTime":"2026-03-12T13:55:53.167738900-05:00[America/Bogota]","screenshots":[{"screenshot":"71b5eff7f0cf3045eaa07898403f6d092f70f7aa1c7251a6a225ef846b17f91f.png","timeStamp":1773341758129,"screenshotName":"71b5eff7f0cf3045eaa07898403f6d092f70f7aa1c7251a6a225ef846b17f91f.png"}],"result":"SUCCESS","precondition":false,"level":0,"children":[{"number":14,"description":"Usuario clicks on enlace al carrito","duration":618,"startTime":"2026-03-12T13:55:53.221939900-05:00[America/Bogota]","screenshots":[{"screenshot":"478dfd1128ea036b37dfe7df8ae80671069f3b29bc4114aeae6730502621a08f.png","timeStamp":1773341753840,"screenshotName":"478dfd1128ea036b37dfe7df8ae80671069f3b29bc4114aeae6730502621a08f.png"}],"result":"SUCCESS","precondition":false,"level":1},{"number":15,"description":"Usuario completa el checkout","duration":4271,"startTime":"2026-03-12T13:55:53.848625100-05:00[America/Bogota]","screenshots":[{"screenshot":"71b5eff7f0cf3045eaa07898403f6d092f70f7aa1c7251a6a225ef846b17f91f.png","timeStamp":1773341758119,"screenshotName":"71b5eff7f0cf3045eaa07898403f6d092f70f7aa1c7251a6a225ef846b17f91f.png"}],"result":"SUCCESS","precondition":false,"level":1,"children":[{"number":16,"description":"Usuario clicks on botón checkout","duration":880,"startTime":"2026-03-12T13:55:53.856482500-05:00[America/Bogota]","screenshots":[{"screenshot":"874a3583baa92179e7edb51b8b2b6476cc4fd0fe5e55a3957a4090056e635bab.png","timeStamp":1773341754736,"screenshotName":"874a3583baa92179e7edb51b8b2b6476cc4fd0fe5e55a3957a4090056e635bab.png"}],"result":"SUCCESS","precondition":false,"level":2},{"number":17,"description":"Usuario enters \u0027Juan\u0027 into nombre","duration":940,"startTime":"2026-03-12T13:55:54.744920700-05:00[America/Bogota]","screenshots":[{"screenshot":"cdd1fe5c94fc0e5be3281c29e448354a2130517c3eb83eb57cfe4366fdc86ecb.png","timeStamp":1773341755684,"screenshotName":"cdd1fe5c94fc0e5be3281c29e448354a2130517c3eb83eb57cfe4366fdc86ecb.png"}],"result":"SUCCESS","precondition":false,"level":2},{"number":18,"description":"Usuario enters \u0027Perez\u0027 into apellido","duration":782,"startTime":"2026-03-12T13:55:55.691064100-05:00[America/Bogota]","screenshots":[{"screenshot":"dc81e3c81e25c9a806ecd5132cf858c83ec4cc8fd388458e7e6b0198cdb43f39.png","timeStamp":1773341756473,"screenshotName":"dc81e3c81e25c9a806ecd5132cf858c83ec4cc8fd388458e7e6b0198cdb43f39.png"}],"result":"SUCCESS","precondition":false,"level":2},{"number":19,"description":"Usuario enters \u002712345\u0027 into código postal","duration":583,"startTime":"2026-03-12T13:55:56.477634-05:00[America/Bogota]","screenshots":[{"screenshot":"4d75168c7eb37171875cb82b922181651f81544c29c320fa24daac9c1c3737f1.png","timeStamp":1773341757060,"screenshotName":"4d75168c7eb37171875cb82b922181651f81544c29c320fa24daac9c1c3737f1.png"}],"result":"SUCCESS","precondition":false,"level":2},{"number":20,"description":"Usuario clicks on continuar","duration":565,"startTime":"2026-03-12T13:55:57.064082400-05:00[America/Bogota]","screenshots":[{"screenshot":"b409318e76e00f5205e6ad56a56f7d1e32db7b3334eb2828efebf471eacb86a6.png","timeStamp":1773341757629,"screenshotName":"b409318e76e00f5205e6ad56a56f7d1e32db7b3334eb2828efebf471eacb86a6.png"}],"result":"SUCCESS","precondition":false,"level":2},{"number":21,"description":"Usuario clicks on finalizar","duration":467,"startTime":"2026-03-12T13:55:57.634396900-05:00[America/Bogota]","screenshots":[{"screenshot":"71b5eff7f0cf3045eaa07898403f6d092f70f7aa1c7251a6a225ef846b17f91f.png","timeStamp":1773341758102,"screenshotName":"71b5eff7f0cf3045eaa07898403f6d092f70f7aa1c7251a6a225ef846b17f91f.png"}],"result":"SUCCESS","precondition":false,"level":2}]}]},{"number":22,"description":"And finishes the purchase","duration":1,"startTime":"2026-03-12T13:55:58.130595800-05:00[America/Bogota]","screenshots":[{"screenshot":"71b5eff7f0cf3045eaa07898403f6d092f70f7aa1c7251a6a225ef846b17f91f.png","timeStamp":1773341758139,"screenshotName":"71b5eff7f0cf3045eaa07898403f6d092f70f7aa1c7251a6a225ef846b17f91f.png"}],"result":"SUCCESS","precondition":false,"level":0},{"number":23,"description":"Then should see a purchase confirmation message","duration":341,"startTime":"2026-03-12T13:55:58.139599300-05:00[America/Bogota]","screenshots":[{"screenshot":"71b5eff7f0cf3045eaa07898403f6d092f70f7aa1c7251a6a225ef846b17f91f.png","timeStamp":1773341758791,"screenshotName":"71b5eff7f0cf3045eaa07898403f6d092f70f7aa1c7251a6a225ef846b17f91f.png"}],"result":"SUCCESS","precondition":false,"level":0,"children":[{"number":24,"description":"Then the confirmation message$$ lambda$1382/0x0000025a2b542518 should be \u0027Thank you for your order!\u0027","duration":161,"startTime":"2026-03-12T13:55:58.317341700-05:00[America/Bogota]","result":"SUCCESS","precondition":false,"level":1}]}],"userStory":{"id":"classpath:features/saucedemo","storyName":"Saucedemo Purchase","displayName":"Saucedemo Purchase","path":"saucedemo","pathElements":[{"name":"saucedemo","description":""}],"narrative":"  As a Saucedemo user\n  I want to log in and make purchases\n  In order to buy products","type":"feature"},"title":"Complete a purchase with one product in cart","description":"","backgroundTitle":"","backgroundDescription":"","tags":[{"name":"checkout","type":"tag","displayName":"checkout"},{"name":"Chrome","type":"context","displayName":"Chrome"},{"name":"Windows","type":"context","displayName":"Windows"},{"name":"Chrome, Windows","type":"context","displayName":"Chrome, Windows"}],"startTime":"2026-03-12T13:55:42.609988400-05:00[America/Bogota]","duration":16183,"projectKey":"","driver":"chrome:usuario","isManualTestingUpToDate":false,"context":"chrome,windows","manual":false,"testSource":"Cucumber","actors":[{"name":"Usuario"}],"result":"SUCCESS"}